[
  {
    "key": "State",
    "value": "AL",
    "row": {
      "AuthName": "City of Alabaster",
      "AuthID": "GNIS_2403069",
      "AuthClass": "City",
      "State": "AL",
      "County": null,
      "City": null,
      "Department": null
    },
    "children": [
      {
        "key": "AuthName",
        "value": "City of Alabaster",
        "row": {
          "AuthName": "City of Alabaster",
          "AuthID": "GNIS_2403069",
          "AuthClass": "City",
          "State": "AL",
          "County": null,
          "City": null,
          "Department": null
        },
        "children": []
      },
      {
        "key": "AuthName",
        "value": "City of Mobile",
        "row": {
          "AuthName": "City of Mobile",
          "AuthID": "GNIS_2404278",
          "AuthClass": "City",
          "State": "AL",
          "County": "Mobile",
          "City": null,
          "Department": null
        },
        "children": []
      }
    ]
  }
]